README.md
setup.cfg
setup.py
snake_on_pygame.egg-info/PKG-INFO
snake_on_pygame.egg-info/SOURCES.txt
snake_on_pygame.egg-info/dependency_links.txt
snake_on_pygame.egg-info/requires.txt
snake_on_pygame.egg-info/top_level.txt
utilities/__init__.py
utilities/text_block.py