Metadata-Version: 2.1
Name: snake-on-pygame
Version: 1.0
Summary: Snake implemented on pygame meant to be used by human and AI agents
Home-page: https://github.com/neves4/snake-on-pygame/
Author: Victor Otavio Andrade das Neves
Author-email: victorneves478@gmail.com
License: UNKNOWN
Project-URL: Source, https://github.com/neves4/snake-on-pygame/
Keywords: snake pygame reinforcement-learning AI python
Platform: UNKNOWN
Classifier: Development Status :: 5 - Production/Stable
Classifier: License :: OSI Approved :: MIT License
Requires-Python: >=2.7
